cog2h3/__init__.py
cog2h3/__version__.py
cog2h3/cog2h3.py
cog2h3-0.0.3.dist-info/entry_points.txt
cog2h3-0.0.3.dist-info/WHEEL
cog2h3-0.0.3.dist-info/METADATA
cog2h3-0.0.3.dist-info/licenses/LICENSE
cog2h3-0.0.3.dist-info/RECORD
