Metadata-Version: 2.1
Name: cog2h3
Version: 0.0.3
Summary: Command line script to convert Cloud Optimized Geotiff to h3 cells and insert to PosgreSQL
License: GPL-3.0-only
Keywords: h3,index,postgresql,cog,tiff,raster
Author-email: Kshitij Raj Sharma <skshitizraj@gmail.com>
Requires-Python: >=3.9
Classifier: Programming Language :: Python :: 3
Classifier: Programming Language :: Python :: 3.10
Classifier: Programming Language :: Python :: 3.11
Classifier: Programming Language :: Python :: 3.9
Classifier: Topic :: Scientific/Engineering :: GIS
Classifier: Topic :: Utilities
Requires-Dist: aiohttp>=3.0.0
Requires-Dist: asyncio>=3.0.0
Requires-Dist: asyncpg>=0.29.0
Requires-Dist: h3>=3.7.0
Requires-Dist: h3ronpy>=0.21.0
Requires-Dist: pandas>=2.0.0
Requires-Dist: rasterio>=1.3.0
Requires-Dist: scikit-learn>=1.5.0
Provides-Extra: docs
Requires-Dist: mkdocs>=1.5.3; extra == "docs"
Requires-Dist: mkdocs-material>=9.4.2; extra == "docs"
Requires-Dist: mkdocstrings-python>=1.7.0; extra == "docs"
Requires-Dist: mkdocs-exclude>=1.0.2; extra == "docs"
Provides-Extra: test
Requires-Dist: pytest>=7.4.2; extra == "test"
Requires-Dist: pytest-mock>=3.14.0; extra == "test"
Requires-Dist: coverage>=7.6.1; extra == "test"
Requires-Dist: coverage-badge>=1.1.2; extra == "test"
Project-URL: documentation, https://github.com/kshitijrajsharma/cog2h3
Project-URL: homepage, https://github.com/kshitijrajsharma/cog2h3
Project-URL: repository, https://github.com/kshitijrajsharma/cog2h3
